openmc_cylindrical_mesh_plotter/__init__.py
openmc_cylindrical_mesh_plotter/_version.py
openmc_cylindrical_mesh_plotter/app.py
openmc_cylindrical_mesh_plotter/core.py
openmc_cylindrical_mesh_plotter/launch.py
openmc_cylindrical_mesh_plotter-0.3.3.dist-info/METADATA
openmc_cylindrical_mesh_plotter-0.3.3.dist-info/WHEEL
openmc_cylindrical_mesh_plotter-0.3.3.dist-info/entry_points.txt
openmc_cylindrical_mesh_plotter-0.3.3.dist-info/top_level.txt
openmc_cylindrical_mesh_plotter-0.3.3.dist-info/RECORD
