Metadata-Version: 2.1
Name: openmc_cylindrical_mesh_plotter
Version: 0.3.3
Summary: A Python package for creating plots of OpenMC cylindrical mesh tallies
Author-email: Jonathan Shimwell <mail@jshimwell.com>
Project-URL: Homepage, https://github.com/fusion-energy/openmc_cylindrical_mesh_plotter
Project-URL: Bug Tracker, https://github.com/fusion-energy/openmc_cylindrical_mesh_plotter/issues
Keywords: cylindrical,mesh,openmc,tally,plot,slice
Classifier: Programming Language :: Python :: 3
Classifier: License :: OSI Approved :: MIT License
Classifier: Operating System :: OS Independent
Requires-Python: >=3.8
Requires-Dist: numpy >=1.21.1
Requires-Dist: matplotlib >=3.4.2
Requires-Dist: pandas
Provides-Extra: gui
Requires-Dist: streamlit ; extra == 'gui'
Provides-Extra: tests
Requires-Dist: pytest ; extra == 'tests'
